{"lastUsed":1575940490868,"path":"D:\/190812\/java","projectCount":19,"recentFiles":[{"path":"\/chap6\/src\/chap6","parentWorkspace":"D:\/190812\/java","name":"Exam7.java","lastModified":1567149703696},{"path":"\/chap14\/src\/chap14","parentWorkspace":"D:\/190812\/java","name":"ListEx3.java","lastModified":1570504722781,"locationURI":"file:\/D:\/190812\/java\/chap14\/src\/chap14\/ListEx3.java"},{"path":"\/chep3\/src\/chep3","parentWorkspace":"D:\/190812\/java","name":"VarEx1.java","lastModified":1569230118340,"locationURI":"file:\/D:\/190812\/java\/chep3\/src\/chep3\/VarEx1.java"},{"path":"\/chap10\/src\/chap10","parentWorkspace":"D:\/190812\/java","name":"InnerEx1.java","lastModified":1568685188382,"locationURI":"file:\/D:\/190812\/java\/chap10\/src\/chap10\/InnerEx1.java"},{"path":"\/chap19\/src\/chap19","parentWorkspace":"D:\/190812\/java","name":"Collection.java","lastModified":1570519447818,"locationURI":"file:\/D:\/190812\/java\/chap19\/src\/chap19\/Collection.java"},{"path":"\/chap7\/src\/chap7","parentWorkspace":"D:\/190812\/java","name":"Exam7.java","lastModified":1567648148773,"locationURI":"file:\/D:\/190812\/java\/chap7\/src\/chap7\/Exam7.java"},{"path":"\/chap12\/src\/chap12","parentWorkspace":"D:\/190812\/java","name":"StringEx1.java","lastModified":1568786848750,"locationURI":"file:\/D:\/190812\/java\/chap12\/src\/chap12\/StringEx1.java"},{"path":"\/chap15\/src\/chap15","parentWorkspace":"D:\/190812\/java","name":"PrintStreamEx2.java","lastModified":1569464588379,"locationURI":"file:\/D:\/190812\/java\/chap15\/src\/chap15\/PrintStreamEx2.java"},{"path":"\/chap8\/src\/chap8","parentWorkspace":"D:\/190812\/java","name":"PackageEx1.java","lastModified":1568101200427,"locationURI":"file:\/D:\/190812\/java\/chap8\/src\/chap8\/PackageEx1.java"},{"path":"\/chap8\/src\/chap8","parentWorkspace":"D:\/190812\/java","name":"FinalValueEx1.java","lastModified":1568017588491,"locationURI":"file:\/D:\/190812\/java\/chap8\/src\/chap8\/FinalValueEx1.java"},{"path":"\/jdbc\/src\/jdbc","parentWorkspace":"D:\/190812\/java","name":"Exam1.java","lastModified":1568101213021,"locationURI":"file:\/D:\/190812\/java\/jdbc\/src\/jdbc\/Exam1.java"},{"path":"\/chap8\/src\/chap8","parentWorkspace":"D:\/190812\/java","name":"BikeEx3.java","lastModified":1567735850167,"locationURI":"file:\/D:\/190812\/java\/chap8\/src\/chap8\/BikeEx3.java"},{"path":"\/chap19\/src\/chap19","parentWorkspace":"D:\/190812\/java","name":"FlatMapEx1.java","lastModified":1569995572455,"locationURI":"file:\/D:\/190812\/java\/chap19\/src\/chap19\/FlatMapEx1.java"},{"path":"\/chap17\/src\/chap17","parentWorkspace":"D:\/190812\/java","name":"InetAddressEx1.java","lastModified":1569826167411,"locationURI":"file:\/D:\/190812\/java\/chap17\/src\/chap17\/InetAddressEx1.java"},{"path":"\/chap7\/src\/chap7","parentWorkspace":"D:\/190812\/java","name":"ThisEx1.java","lastModified":1567651331435,"locationURI":"file:\/D:\/190812\/java\/chap7\/src\/chap7\/ThisEx1.java"},{"path":"\/chap15","parentWorkspace":"D:\/190812\/java","name":"bufferd.txt","lastModified":1569460687793,"locationURI":"file:\/D:\/190812\/java\/chap15\/bufferd.txt"},{"path":"\/chap12\/src\/chap12","parentWorkspace":"D:\/190812\/java","name":"e190918.java","lastModified":1568853953006,"locationURI":"file:\/D:\/190812\/java\/chap12\/src\/chap12\/e190918.java"},{"path":"\/chap10\/src\/chap10","parentWorkspace":"D:\/190812\/java","name":"InnerEx4.java","lastModified":1568690430044,"locationURI":"file:\/D:\/190812\/java\/chap10\/src\/chap10\/InnerEx4.java"},{"path":"\/chap5\/src\/chap5","parentWorkspace":"D:\/190812\/java","name":"ex190827.java","lastModified":1566953317647},{"path":"\/chap15\/src\/chap15","parentWorkspace":"D:\/190812\/java","name":"Exam3.java","lastModified":1570504722781,"locationURI":"file:\/D:\/190812\/java\/chap15\/src\/chap15\/Exam3.java"},{"path":"\/chap18\/src\/chap18","parentWorkspace":"D:\/190812\/java","name":"Exam3.java","lastModified":1569984170755,"locationURI":"file:\/D:\/190812\/java\/chap18\/src\/chap18\/Exam3.java"},{"path":"\/chap8\/src\/chap8\/packtest","parentWorkspace":"D:\/190812\/java","name":"Pack2.java","lastModified":1567998168032,"locationURI":"file:\/D:\/190812\/java\/chap8\/src\/chap8\/packtest\/Pack2.java"},{"path":"\/chap12\/src\/chap12","parentWorkspace":"D:\/190812\/java","name":"WrapperEx5.java","lastModified":1568876074101,"locationURI":"file:\/D:\/190812\/java\/chap12\/src\/chap12\/WrapperEx5.java"},{"path":"\/chap18\/src\/chap18","parentWorkspace":"D:\/190812\/java","name":"LambadaEx2.java","lastModified":1569907184136,"locationURI":"file:\/D:\/190812\/java\/chap18\/src\/chap18\/LambadaEx2.java"},{"path":"\/chap6\/src\/chap6","parentWorkspace":"D:\/190812\/java","name":"Exam1.java","lastModified":1570497693564},{"path":"\/chap12\/src\/chap12","parentWorkspace":"D:\/190812\/java","name":"MathEx2.java","lastModified":1568871580789,"locationURI":"file:\/D:\/190812\/java\/chap12\/src\/chap12\/MathEx2.java"},{"path":"\/chap6\/src\/chap6","parentWorkspace":"D:\/190812\/java","name":"ArrayEx13.java","lastModified":1567406394598,"locationURI":"file:\/D:\/190812\/java\/chap6\/src\/chap6\/ArrayEx13.java"},{"path":"\/chap8\/src\/chap8","parentWorkspace":"D:\/190812\/java","name":"ModifierEx1.java","lastModified":1568101200427,"locationURI":"file:\/D:\/190812\/java\/chap8\/src\/chap8\/ModifierEx1.java"},{"path":"\/chap19\/src\/chap19","parentWorkspace":"D:\/190812\/java","name":"e191002.java","lastModified":1570497693564,"locationURI":"file:\/D:\/190812\/java\/chap19\/src\/chap19\/e191002.java"},{"path":"\/chap12\/src\/chap12","parentWorkspace":"D:\/190812\/java","name":"Exam7.java","lastModified":1568962812891,"locationURI":"file:\/D:\/190812\/java\/chap12\/src\/chap12\/Exam7.java"},{"path":"\/chap5\/src\/chap5","parentWorkspace":"D:\/190812\/java","name":"Exam11.java","lastModified":1566953591393},{"path":"\/chap8\/src\/chap8","parentWorkspace":"D:\/190812\/java","name":"ShampEx1.java","lastModified":1567994048088,"locationURI":"file:\/D:\/190812\/java\/chap8\/src\/chap8\/ShampEx1.java"},{"path":"\/chap16\/src\/chap16","parentWorkspace":"D:\/190812\/java","name":"ThreadEx13.java","lastModified":1569818303436,"locationURI":"file:\/D:\/190812\/java\/chap16\/src\/chap16\/ThreadEx13.java"},{"path":"\/chap17\/src\/chap17","parentWorkspace":"D:\/190812\/java","name":"SimpleWebServerEx1.java","lastModified":1569897394257,"locationURI":"file:\/D:\/190812\/java\/chap17\/src\/chap17\/SimpleWebServerEx1.java"},{"path":"\/chap7\/src\/chap7","parentWorkspace":"D:\/190812\/java","name":"ex190903.java","lastModified":1567559521156,"locationURI":"file:\/D:\/190812\/java\/chap7\/src\/chap7\/ex190903.java"},{"path":"\/chap7\/src\/chap7","parentWorkspace":"D:\/190812\/java","name":"OverloadEx1.java","lastModified":1567565333312,"locationURI":"file:\/D:\/190812\/java\/chap7\/src\/chap7\/OverloadEx1.java"},{"path":"\/chap19\/src\/chap19","parentWorkspace":"D:\/190812\/java","name":"SortedEx2.java","lastModified":1570153425274,"locationURI":"file:\/D:\/190812\/java\/chap19\/src\/chap19\/SortedEx2.java"},{"path":"\/chap8\/src\/chap8","parentWorkspace":"D:\/190812\/java","name":"Finalclass.java","lastModified":1568101200427,"locationURI":"file:\/D:\/190812\/java\/chap8\/src\/chap8\/Finalclass.java"},{"path":"\/chap11\/src\/chap11","parentWorkspace":"D:\/190812\/java","name":"ExeptionEx5.java","lastModified":1568796186036,"locationURI":"file:\/D:\/190812\/java\/chap11\/src\/chap11\/ExeptionEx5.java"},{"path":"\/chap12\/src\/chap12","parentWorkspace":"D:\/190812\/java","name":"DateEx1.java","lastModified":1568947916945,"locationURI":"file:\/D:\/190812\/java\/chap12\/src\/chap12\/DateEx1.java"},{"path":"\/chap12\/src\/chap12","parentWorkspace":"D:\/190812\/java","name":"ScannerEx2.java","lastModified":1568943995170,"locationURI":"file:\/D:\/190812\/java\/chap12\/src\/chap12\/ScannerEx2.java"},{"path":"\/chap7\/src\/chap7","parentWorkspace":"D:\/190812\/java","name":"Exam4.java","lastModified":1567495068833,"locationURI":"file:\/D:\/190812\/java\/chap7\/src\/chap7\/Exam4.java"},{"path":"\/chap9\/src\/chap9","parentWorkspace":"D:\/190812\/java","name":"ex190910.java","lastModified":1568106306672,"locationURI":"file:\/D:\/190812\/java\/chap9\/src\/chap9\/ex190910.java"},{"path":"\/chap11\/src\/chap11","parentWorkspace":"D:\/190812\/java","name":"ExeptionEx1.java","lastModified":1568772670670,"locationURI":"file:\/D:\/190812\/java\/chap11\/src\/chap11\/ExeptionEx1.java"},{"path":"\/chap12\/src\/chap12","parentWorkspace":"D:\/190812\/java","name":"RandomEx1.java","lastModified":1568877484048,"locationURI":"file:\/D:\/190812\/java\/chap12\/src\/chap12\/RandomEx1.java"},{"path":"\/chap12\/src\/chap12","parentWorkspace":"D:\/190812\/java","name":"RegularEx2.java","lastModified":1569201496437,"locationURI":"file:\/D:\/190812\/java\/chap12\/src\/chap12\/RegularEx2.java"},{"path":"\/chap14\/src\/chap14","parentWorkspace":"D:\/190812\/java","name":"SetEx2.java","lastModified":1569318870076,"locationURI":"file:\/D:\/190812\/java\/chap14\/src\/chap14\/SetEx2.java"},{"path":"\/chap15\/src\/chap15","parentWorkspace":"D:\/190812\/java","name":"ObjectInputStreamEx1.java","lastModified":1570497693564,"locationURI":"file:\/D:\/190812\/java\/chap15\/src\/chap15\/ObjectInputStreamEx1.java"},{"path":"\/chap16\/src\/chap16","parentWorkspace":"D:\/190812\/java","name":"ThreadEx10.java","lastModified":1569809685581,"locationURI":"file:\/D:\/190812\/java\/chap16\/src\/chap16\/ThreadEx10.java"},{"path":"\/chap6\/src\/chap6","parentWorkspace":"D:\/190812\/java","name":"Exam11.java","lastModified":1567392019757},{"path":"\/chap15\/src\/chap15","parentWorkspace":"D:\/190812\/java","name":"e190925.java","lastModified":1570504722781,"locationURI":"file:\/D:\/190812\/java\/chap15\/src\/chap15\/e190925.java"},{"path":"\/chap14","parentWorkspace":"D:\/190812\/java","name":"b.properties","lastModified":1569375747596,"locationURI":"file:\/D:\/190812\/java\/chap14\/b.properties"},{"path":"\/chap8\/src\/chap8","parentWorkspace":"D:\/190812\/java","name":"Exam3.java","lastModified":1568101200427,"locationURI":"file:\/D:\/190812\/java\/chap8\/src\/chap8\/Exam3.java"},{"path":"\/chap6\/src\/chap6","parentWorkspace":"D:\/190812\/java","name":"Exam4.java","lastModified":1567503692579},{"path":"\/chap5\/src\/chap5","parentWorkspace":"D:\/190812\/java","name":"Exam12.java","lastModified":1566956001969},{"path":"\/chap16\/src\/chap16","parentWorkspace":"D:\/190812\/java","name":"Exam3.java","lastModified":1569920776526,"locationURI":"file:\/D:\/190812\/java\/chap16\/src\/chap16\/Exam3.java"},{"path":"\/chap12\/src\/chap12","parentWorkspace":"D:\/190812\/java","name":"Exam6.java","lastModified":1568961873973,"locationURI":"file:\/D:\/190812\/java\/chap12\/src\/chap12\/Exam6.java"},{"path":"\/chap8\/src\/chap8","parentWorkspace":"D:\/190812\/java","name":"SuperEx.java","lastModified":1567674099526,"locationURI":"file:\/D:\/190812\/java\/chap8\/src\/chap8\/SuperEx.java"},{"path":"\/chap16\/src\/chap16","parentWorkspace":"D:\/190812\/java","name":"ThreadEx1.java","lastModified":1569920776245,"locationURI":"file:\/D:\/190812\/java\/chap16\/src\/chap16\/ThreadEx1.java"},{"path":"\/chap6\/src\/chap6","parentWorkspace":"D:\/190812\/java","name":"Exam12.java","lastModified":1570497693564,"locationURI":"file:\/D:\/190812\/java\/chap6\/src\/chap6\/Exam12.java"},{"path":"\/syj20191008","parentWorkspace":"D:\/190812\/java","name":"emp.txt","lastModified":1570514563149,"locationURI":"file:\/D:\/190812\/java\/syj20191008\/emp.txt"},{"path":"\/jdbc\/src\/jdbc","parentWorkspace":"D:\/190812\/java","name":"JdbcEx1.java","lastModified":1568192560983,"locationURI":"file:\/D:\/190812\/java\/jdbc\/src\/jdbc\/JdbcEx1.java"},{"path":"\/chap5\/src\/chap5","parentWorkspace":"D:\/190812\/java","name":"ex190826.java","lastModified":1566866583746},{"path":"\/chap18\/src\/chap18","parentWorkspace":"D:\/190812\/java","name":"LambadaEx3.java","lastModified":1569907182066,"locationURI":"file:\/D:\/190812\/java\/chap18\/src\/chap18\/LambadaEx3.java"},{"path":"\/chap6\/src\/chap6","parentWorkspace":"D:\/190812\/java","name":"Exam3.java","lastModified":1566976428704},{"path":"\/chap19\/src\/chap19","parentWorkspace":"D:\/190812\/java","name":"FilterStreamEx1.java","lastModified":1569993685324,"locationURI":"file:\/D:\/190812\/java\/chap19\/src\/chap19\/FilterStreamEx1.java"},{"path":"\/chap7\/src\/chap7","parentWorkspace":"D:\/190812\/java","name":"Exam6.java","lastModified":1567579981188,"locationURI":"file:\/D:\/190812\/java\/chap7\/src\/chap7\/Exam6.java"},{"path":"\/chap9\/src\/chap9","parentWorkspace":"D:\/190812\/java","name":"ComplexerEx1.java","lastModified":1570519455330,"locationURI":"file:\/D:\/190812\/java\/chap9\/src\/chap9\/ComplexerEx1.java"},{"path":"\/chap15\/src\/chap15","parentWorkspace":"D:\/190812\/java","name":"PrintStreamEx1.java","lastModified":1569462714529,"locationURI":"file:\/D:\/190812\/java\/chap15\/src\/chap15\/PrintStreamEx1.java"},{"path":"\/chap17\/src\/chap17","parentWorkspace":"D:\/190812\/java","name":"EchoClientEx1.java","lastModified":1569898362450,"locationURI":"file:\/D:\/190812\/java\/chap17\/src\/chap17\/EchoClientEx1.java"},{"path":"\/test0916\/src\/test0916","parentWorkspace":"D:\/190812\/java","name":"Syjfamily.java","lastModified":1568617626500,"locationURI":"file:\/D:\/190812\/java\/test0916\/src\/test0916\/Syjfamily.java"},{"path":"\/chap8\/src\/chap8","parentWorkspace":"D:\/190812\/java","name":"BikeEx4.java","lastModified":1567737603713,"locationURI":"file:\/D:\/190812\/java\/chap8\/src\/chap8\/BikeEx4.java"},{"path":"\/chap14\/src\/chap14","parentWorkspace":"D:\/190812\/java","name":"SetEx4.java","lastModified":1570524522956,"locationURI":"file:\/D:\/190812\/java\/chap14\/src\/chap14\/SetEx4.java"},{"path":"\/chap14\/src\/chap14","parentWorkspace":"D:\/190812\/java","name":"Exam4.java","lastModified":1569372647524,"locationURI":"file:\/D:\/190812\/java\/chap14\/src\/chap14\/Exam4.java"},{"path":"\/chap6\/src\/chap6","parentWorkspace":"D:\/190812\/java","name":"ex190902.java","lastModified":1570497693564,"locationURI":"file:\/D:\/190812\/java\/chap6\/src\/chap6\/ex190902.java"},{"path":"\/chap7\/src\/chap7","parentWorkspace":"D:\/190812\/java","name":"Exam3.java","lastModified":1567491186874,"locationURI":"file:\/D:\/190812\/java\/chap7\/src\/chap7\/Exam3.java"},{"path":"\/chap12\/src\/chap12","parentWorkspace":"D:\/190812\/java","name":"CalendarEx1.java","lastModified":1568957428851,"locationURI":"file:\/D:\/190812\/java\/chap12\/src\/chap12\/CalendarEx1.java"},{"path":"\/chap14\/src\/chap14","parentWorkspace":"D:\/190812\/java","name":"SetEx1.java","lastModified":1569318044012,"locationURI":"file:\/D:\/190812\/java\/chap14\/src\/chap14\/SetEx1.java"},{"path":"\/chap7\/src\/chap7","parentWorkspace":"D:\/190812\/java","name":"ConstructorEx1.java","lastModified":1567573003246,"locationURI":"file:\/D:\/190812\/java\/chap7\/src\/chap7\/ConstructorEx1.java"},{"path":"\/chap18\/src\/chap18","parentWorkspace":"D:\/190812\/java","name":"LambadaEx6.java","lastModified":1569913299012,"locationURI":"file:\/D:\/190812\/java\/chap18\/src\/chap18\/LambadaEx6.java"},{"path":"\/chap7\/src\/chap7","parentWorkspace":"D:\/190812\/java","name":"SonataEx1.java","lastModified":1567760735729,"locationURI":"file:\/D:\/190812\/java\/chap7\/src\/chap7\/SonataEx1.java"},{"path":"\/chap12\/src\/chap12","parentWorkspace":"D:\/190812\/java","name":"Exam1.java","lastModified":1568794300061,"locationURI":"file:\/D:\/190812\/java\/chap12\/src\/chap12\/Exam1.java"},{"path":"\/chap16\/src\/chap16","parentWorkspace":"D:\/190812\/java","name":"ThreadEx8.java","lastModified":1569806172786,"locationURI":"file:\/D:\/190812\/java\/chap16\/src\/chap16\/ThreadEx8.java"},{"path":"\/jdbc\/src\/jdbc","parentWorkspace":"D:\/190812\/java","name":"JdbcEX2.java","lastModified":1568096097175,"locationURI":"file:\/D:\/190812\/java\/jdbc\/src\/jdbc\/JdbcEX2.java"},{"path":"\/chap7\/src\/chap7","parentWorkspace":"D:\/190812\/java","name":"ConstratorEx2.java","lastModified":1567575532577,"locationURI":"file:\/D:\/190812\/java\/chap7\/src\/chap7\/ConstratorEx2.java"},{"path":"\/chap15\/src\/chap15","parentWorkspace":"D:\/190812\/java","name":"FileEx1.java","lastModified":1569477112696,"locationURI":"file:\/D:\/190812\/java\/chap15\/src\/chap15\/FileEx1.java"},{"path":"\/chap8\/src\/chap8","parentWorkspace":"D:\/190812\/java","name":"FinalMethod.java","lastModified":1568101200427,"locationURI":"file:\/D:\/190812\/java\/chap8\/src\/chap8\/FinalMethod.java"},{"path":"\/chap15\/src\/chap15","parentWorkspace":"D:\/190812\/java","name":"FileReaderEx1.java","lastModified":1570497693564,"locationURI":"file:\/D:\/190812\/java\/chap15\/src\/chap15\/FileReaderEx1.java"},{"path":"\/chap16\/src\/chap16","parentWorkspace":"D:\/190812\/java","name":"Exam2.java","lastModified":1569562594660,"locationURI":"file:\/D:\/190812\/java\/chap16\/src\/chap16\/Exam2.java"},{"path":"\/jdbc\/src\/jdbc","parentWorkspace":"D:\/190812\/java","name":"JdbcEx6.java","lastModified":1568192560968,"locationURI":"file:\/D:\/190812\/java\/jdbc\/src\/jdbc\/JdbcEx6.java"},{"path":"\/chap12\/src\/chap12","parentWorkspace":"D:\/190812\/java","name":"WrapperEx1.java","lastModified":1568873011625,"locationURI":"file:\/D:\/190812\/java\/chap12\/src\/chap12\/WrapperEx1.java"},{"path":"\/syj20191008\/src\/syj20191008","parentWorkspace":"D:\/190812\/java","name":"Exam1.java","lastModified":1570518954401,"locationURI":"file:\/D:\/190812\/java\/syj20191008\/src\/syj20191008\/Exam1.java"},{"path":"\/chap8\/src\/chap8\/packtest","parentWorkspace":"D:\/190812\/java","name":"Modifier2.java","lastModified":1568005618184,"locationURI":"file:\/D:\/190812\/java\/chap8\/src\/chap8\/packtest\/Modifier2.java"},{"path":"\/test0916\/src\/test0916","parentWorkspace":"D:\/190812\/java","name":"Exam1.java","lastModified":1570516447804,"locationURI":"file:\/D:\/190812\/java\/test0916\/src\/test0916\/Exam1.java"},{"path":"\/chap9\/src\/chap9","parentWorkspace":"D:\/190812\/java","name":"Exam1.java","lastModified":1568020628067,"locationURI":"file:\/D:\/190812\/java\/chap9\/src\/chap9\/Exam1.java"},{"path":"\/chap11\/src\/chap11","parentWorkspace":"D:\/190812\/java","name":"e190917.java","lastModified":1568769638623,"locationURI":"file:\/D:\/190812\/java\/chap11\/src\/chap11\/e190917.java"},{"path":"\/chap16\/src\/chap16","parentWorkspace":"D:\/190812\/java","name":"ThreadEx11.java","lastModified":1569810070048,"locationURI":"file:\/D:\/190812\/java\/chap16\/src\/chap16\/ThreadEx11.java"},{"path":"\/chep4\/src\/chep4","parentWorkspace":"D:\/190812\/java","name":"OpEx2.java","lastModified":1567586647910,"locationURI":"file:\/D:\/190812\/java\/chep4\/src\/chep4\/OpEx2.java"},{"path":"\/chap8\/src\/chap8","parentWorkspace":"D:\/190812\/java","name":"Exam4.java","lastModified":1567997028299,"locationURI":"file:\/D:\/190812\/java\/chap8\/src\/chap8\/Exam4.java"},{"path":"\/chap10\/src\/chap10","parentWorkspace":"D:\/190812\/java","name":"InnerEx3.java","lastModified":1568686577169,"locationURI":"file:\/D:\/190812\/java\/chap10\/src\/chap10\/InnerEx3.java"},{"path":"\/chap15\/src\/chap15","parentWorkspace":"D:\/190812\/java","name":"Exam2.java","lastModified":1570497693564,"locationURI":"file:\/D:\/190812\/java\/chap15\/src\/chap15\/Exam2.java"},{"path":"\/chap12\/src\/chap12","parentWorkspace":"D:\/190812\/java","name":"StringEx3.java","lastModified":1568855329493,"locationURI":"file:\/D:\/190812\/java\/chap12\/src\/chap12\/StringEx3.java"},{"path":"\/chap15\/src\/chap15","parentWorkspace":"D:\/190812\/java","name":"FileInputStreamEx1.java","lastModified":1570497693564,"locationURI":"file:\/D:\/190812\/java\/chap15\/src\/chap15\/FileInputStreamEx1.java"},{"path":"\/chap11\/src\/chap11","parentWorkspace":"D:\/190812\/java","name":"ExeptionEx8.java","lastModified":1568771789722,"locationURI":"file:\/D:\/190812\/java\/chap11\/src\/chap11\/ExeptionEx8.java"},{"path":"\/chap12\/src\/chap12","parentWorkspace":"D:\/190812\/java","name":"Test0919_2.java","lastModified":1568882503584,"locationURI":"file:\/D:\/190812\/java\/chap12\/src\/chap12\/Test0919_2.java"},{"path":"\/chap12","parentWorkspace":"D:\/190812\/java","name":"score.txt","lastModified":1568941909986,"locationURI":"file:\/D:\/190812\/java\/chap12\/score.txt"},{"path":"\/chap8\/src\/chap8","parentWorkspace":"D:\/190812\/java","name":"SuperEx1.java","lastModified":1567736488115,"locationURI":"file:\/D:\/190812\/java\/chap8\/src\/chap8\/SuperEx1.java"},{"path":"\/chap16\/src\/chap16","parentWorkspace":"D:\/190812\/java","name":"Exam5.java","lastModified":1569822792910,"locationURI":"file:\/D:\/190812\/java\/chap16\/src\/chap16\/Exam5.java"},{"path":"\/chap7\/src\/chap7","parentWorkspace":"D:\/190812\/java","name":"MathEx2.java","lastModified":1567561868473,"locationURI":"file:\/D:\/190812\/java\/chap7\/src\/chap7\/MathEx2.java"},{"path":"\/chap8\/src\/chap8","parentWorkspace":"D:\/190812\/java","name":"BindingEx1.java","lastModified":1567738720948,"locationURI":"file:\/D:\/190812\/java\/chap8\/src\/chap8\/BindingEx1.java"},{"path":"\/chap5\/src\/chap5","parentWorkspace":"D:\/190812\/java","name":"Exam14.java","lastModified":1566960136905},{"path":"\/chap11\/src\/chap11","parentWorkspace":"D:\/190812\/java","name":"Exam4.java","lastModified":1568776676895,"locationURI":"file:\/D:\/190812\/java\/chap11\/src\/chap11\/Exam4.java"},{"path":"\/chap11\/src\/chap11","parentWorkspace":"D:\/190812\/java","name":"Exam1.java","lastModified":1568702761041,"locationURI":"file:\/D:\/190812\/java\/chap11\/src\/chap11\/Exam1.java"},{"path":"\/chap7\/src\/chap7","parentWorkspace":"D:\/190812\/java","name":"LocalValEx.java","lastModified":1567760735541,"locationURI":"file:\/D:\/190812\/java\/chap7\/src\/chap7\/LocalValEx.java"},{"path":"\/chep4\/src\/chep4","parentWorkspace":"D:\/190812\/java","name":"OpEx5.java","lastModified":1567587166036,"locationURI":"file:\/D:\/190812\/java\/chep4\/src\/chep4\/OpEx5.java"},{"path":"\/chap14\/src\/chap14","parentWorkspace":"D:\/190812\/java","name":"Exam2.java","lastModified":1569313770466,"locationURI":"file:\/D:\/190812\/java\/chap14\/src\/chap14\/Exam2.java"},{"path":"\/chap15\/src\/chap15","parentWorkspace":"D:\/190812\/java","name":"ProcessEx1.java","lastModified":1569482777375,"locationURI":"file:\/D:\/190812\/java\/chap15\/src\/chap15\/ProcessEx1.java"},{"path":"\/chap7\/src\/chap7","parentWorkspace":"D:\/190812\/java","name":"Exam1.java","lastModified":1567480711946,"locationURI":"file:\/D:\/190812\/java\/chap7\/src\/chap7\/Exam1.java"},{"path":"\/chap18\/src\/chap18","parentWorkspace":"D:\/190812\/java","name":"LambadaEx9.java","lastModified":1569981356102,"locationURI":"file:\/D:\/190812\/java\/chap18\/src\/chap18\/LambadaEx9.java"},{"path":"\/chap19\/src\/chap19","parentWorkspace":"D:\/190812\/java","name":"IteratorEx1.java","lastModified":1570149363065,"locationURI":"file:\/D:\/190812\/java\/chap19\/src\/chap19\/IteratorEx1.java"},{"path":"\/chap8\/src\/chap8","parentWorkspace":"D:\/190812\/java","name":"InstanceOfEx1.java","lastModified":1568101200427,"locationURI":"file:\/D:\/190812\/java\/chap8\/src\/chap8\/InstanceOfEx1.java"},{"path":"\/chap6\/src\/chap6","parentWorkspace":"D:\/190812\/java","name":"Exam6.java","lastModified":1570497693564},{"path":"\/chap14\/src\/chap14","parentWorkspace":"D:\/190812\/java","name":"ListEx2.java","lastModified":1569215563137,"locationURI":"file:\/D:\/190812\/java\/chap14\/src\/chap14\/ListEx2.java"},{"path":"\/chap8\/src\/chap8","parentWorkspace":"D:\/190812\/java","name":"Exam1.java","lastModified":1567730615879,"locationURI":"file:\/D:\/190812\/java\/chap8\/src\/chap8\/Exam1.java"},{"path":"\/chap8\/src\/chap8","parentWorkspace":"D:\/190812\/java","name":"ex190905.java","lastModified":1567730622976,"locationURI":"file:\/D:\/190812\/java\/chap8\/src\/chap8\/ex190905.java"},{"path":"\/chap8\/src\/chap8","parentWorkspace":"D:\/190812\/java","name":"SingletonEx.java","lastModified":1568007651243,"locationURI":"file:\/D:\/190812\/java\/chap8\/src\/chap8\/SingletonEx.java"},{"path":"\/chap12\/src\/chap12","parentWorkspace":"D:\/190812\/java","name":"WrapperEx4.java","lastModified":1568875449179,"locationURI":"file:\/D:\/190812\/java\/chap12\/src\/chap12\/WrapperEx4.java"},{"path":"\/chap18\/src\/chap18","parentWorkspace":"D:\/190812\/java","name":"LambadaEx1.java","lastModified":1569908026522,"locationURI":"file:\/D:\/190812\/java\/chap18\/src\/chap18\/LambadaEx1.java"},{"path":"\/chap16\/src\/chap16","parentWorkspace":"D:\/190812\/java","name":"ThreadEx3.java","lastModified":1569563753440,"locationURI":"file:\/D:\/190812\/java\/chap16\/src\/chap16\/ThreadEx3.java"},{"path":"\/chap6\/src\/chap6","parentWorkspace":"D:\/190812\/java","name":"Array1.java","lastModified":1566966738938},{"path":"\/jdbc\/src\/jdbc","parentWorkspace":"D:\/190812\/java","name":"JdbcEx3.java","lastModified":1568192560983,"locationURI":"file:\/D:\/190812\/java\/jdbc\/src\/jdbc\/JdbcEx3.java"},{"path":"\/chap12\/src\/chap12","parentWorkspace":"D:\/190812\/java","name":"Exam4.java","lastModified":1568863324583,"locationURI":"file:\/D:\/190812\/java\/chap12\/src\/chap12\/Exam4.java"},{"path":"\/chap7\/src\/chap7","parentWorkspace":"D:\/190812\/java","name":"SonataEx2.java","lastModified":1567499797316,"locationURI":"file:\/D:\/190812\/java\/chap7\/src\/chap7\/SonataEx2.java"},{"path":"\/chap12\/src\/chap12","parentWorkspace":"D:\/190812\/java","name":"Exam2.java","lastModified":1568857372883,"locationURI":"file:\/D:\/190812\/java\/chap12\/src\/chap12\/Exam2.java"},{"path":"\/chap7\/src\/chap7","parentWorkspace":"D:\/190812\/java","name":"ParameterEx1.java","lastModified":1567761232802,"locationURI":"file:\/D:\/190812\/java\/chap7\/src\/chap7\/ParameterEx1.java"},{"path":"\/chap12\/src\/chap12","parentWorkspace":"D:\/190812\/java","name":"EqualsEx2.java","lastModified":1568784090724,"locationURI":"file:\/D:\/190812\/java\/chap12\/src\/chap12\/EqualsEx2.java"},{"path":"\/chap8\/src\/chap8","parentWorkspace":"D:\/190812\/java","name":"Exam2.java","lastModified":1568101200099,"locationURI":"file:\/D:\/190812\/java\/chap8\/src\/chap8\/Exam2.java"},{"path":"\/chap16\/src\/chap16","parentWorkspace":"D:\/190812\/java","name":"ThreadEx9.java","lastModified":1569808338010,"locationURI":"file:\/D:\/190812\/java\/chap16\/src\/chap16\/ThreadEx9.java"},{"path":"\/chap11\/src\/chap11","parentWorkspace":"D:\/190812\/java","name":"ExeptionEx6.java","lastModified":1568797922725,"locationURI":"file:\/D:\/190812\/java\/chap11\/src\/chap11\/ExeptionEx6.java"},{"path":"\/chap14\/src\/chap14","parentWorkspace":"D:\/190812\/java","name":"Exam5.java","lastModified":1569308249984,"locationURI":"file:\/D:\/190812\/java\/chap14\/src\/chap14\/Exam5.java"},{"path":"\/chap15\/src\/chap15","parentWorkspace":"D:\/190812\/java","name":"BufferedReaderEx1.java","lastModified":1570504722781,"locationURI":"file:\/D:\/190812\/java\/chap15\/src\/chap15\/BufferedReaderEx1.java"},{"path":"\/chap19\/src\/chap19","parentWorkspace":"D:\/190812\/java","name":"IntStreamEx1.java","lastModified":1569993254329,"locationURI":"file:\/D:\/190812\/java\/chap19\/src\/chap19\/IntStreamEx1.java"},{"path":"\/chap11\/src\/chap11","parentWorkspace":"D:\/190812\/java","name":"Exam2.java","lastModified":1568704167569,"locationURI":"file:\/D:\/190812\/java\/chap11\/src\/chap11\/Exam2.java"},{"path":"\/chap11\/src\/chap11","parentWorkspace":"D:\/190812\/java","name":"ExeptionEx3.java","lastModified":1568696313244,"locationURI":"file:\/D:\/190812\/java\/chap11\/src\/chap11\/ExeptionEx3.java"},{"path":"\/chap7\/src\/chap7","parentWorkspace":"D:\/190812\/java","name":"Exam2.java","lastModified":1567480866507,"locationURI":"file:\/D:\/190812\/java\/chap7\/src\/chap7\/Exam2.java"},{"path":"\/test0916\/src\/test0916","parentWorkspace":"D:\/190812\/java","name":"test191008.java","lastModified":1570509221860,"locationURI":"file:\/D:\/190812\/java\/test0916\/src\/test0916\/test191008.java"},{"path":"\/chap11\/src\/chap11","parentWorkspace":"D:\/190812\/java","name":"ExeptionEx9.java","lastModified":1568776083634,"locationURI":"file:\/D:\/190812\/java\/chap11\/src\/chap11\/ExeptionEx9.java"},{"path":"\/chap15\/src\/chap15","parentWorkspace":"D:\/190812\/java","name":"ObjectOutputStreamEx2.java","lastModified":1569482777469,"locationURI":"file:\/D:\/190812\/java\/chap15\/src\/chap15\/ObjectOutputStreamEx2.java"},{"path":"\/chap18\/src\/chap18","parentWorkspace":"D:\/190812\/java","name":"LambadaEx4.java","lastModified":1569911962558,"locationURI":"file:\/D:\/190812\/java\/chap18\/src\/chap18\/LambadaEx4.java"},{"path":"\/chap15\/src\/chap15","parentWorkspace":"D:\/190812\/java","name":"FileOutputStreamEx2.java","lastModified":1569394196575,"locationURI":"file:\/D:\/190812\/java\/chap15\/src\/chap15\/FileOutputStreamEx2.java"},{"path":"\/chap5\/src\/chap5","parentWorkspace":"D:\/190812\/java","name":"Exam13.java","lastModified":1566958105988},{"path":"\/chap6\/src\/chap6","parentWorkspace":"D:\/190812\/java","name":"ex190828.java","lastModified":1570497693564,"locationURI":"file:\/D:\/190812\/java\/chap6\/src\/chap6\/ex190828.java"},{"path":"\/chap6\/src\/chap6","parentWorkspace":"D:\/190812\/java","name":"ArrayEx11.java","lastModified":1567404102807,"locationURI":"file:\/D:\/190812\/java\/chap6\/src\/chap6\/ArrayEx11.java"},{"path":"\/chap12\/src\/chap12","parentWorkspace":"D:\/190812\/java","name":"Exam5.java","lastModified":1568881983617,"locationURI":"file:\/D:\/190812\/java\/chap12\/src\/chap12\/Exam5.java"},{"path":"\/chap8\/src\/chap8","parentWorkspace":"D:\/190812\/java","name":"PhoneEx1.java","lastModified":1568020628067,"locationURI":"file:\/D:\/190812\/java\/chap8\/src\/chap8\/PhoneEx1.java"},{"path":"\/chap14\/src\/chap14","parentWorkspace":"D:\/190812\/java","name":"e190923.java","lastModified":1570776999099,"locationURI":"file:\/D:\/190812\/java\/chap14\/src\/chap14\/e190923.java"},{"path":"\/chap19\/src\/chap19","parentWorkspace":"D:\/190812\/java","name":"MapEx1.java","lastModified":1569997275886,"locationURI":"file:\/D:\/190812\/java\/chap19\/src\/chap19\/MapEx1.java"},{"path":"\/chap15\/src\/chap15","parentWorkspace":"D:\/190812\/java","name":"e190926.java","lastModified":1570504722781,"locationURI":"file:\/D:\/190812\/java\/chap15\/src\/chap15\/e190926.java"},{"path":"\/chap6\/src\/chap6","parentWorkspace":"D:\/190812\/java","name":"Exam5.java","lastModified":1567045931936},{"path":"\/chap14\/src\/chap14","parentWorkspace":"D:\/190812\/java","name":"ListEx1.java","lastModified":1569230175347,"locationURI":"file:\/D:\/190812\/java\/chap14\/src\/chap14\/ListEx1.java"},{"path":"\/chap9\/src\/chap9","parentWorkspace":"D:\/190812\/java","name":"e0916.java","lastModified":1568624555100,"locationURI":"file:\/D:\/190812\/java\/chap9\/src\/chap9\/e0916.java"},{"path":"\/jdbc\/src\/jdbc","parentWorkspace":"D:\/190812\/java","name":"Exam2.java","lastModified":1568169545527,"locationURI":"file:\/D:\/190812\/java\/jdbc\/src\/jdbc\/Exam2.java"},{"path":"\/chap17","parentWorkspace":"D:\/190812\/java","name":"index.html","lastModified":1569830276218,"locationURI":"file:\/D:\/190812\/java\/chap17\/index.html"},{"path":"\/chap18\/src\/chap18","parentWorkspace":"D:\/190812\/java","name":"Exam1.java","lastModified":1569908163483,"locationURI":"file:\/D:\/190812\/java\/chap18\/src\/chap18\/Exam1.java"},{"path":"\/chap7\/src\/chap7","parentWorkspace":"D:\/190812\/java","name":"PhoneEx1.java","lastModified":1567477087561,"locationURI":"file:\/D:\/190812\/java\/chap7\/src\/chap7\/PhoneEx1.java"},{"path":"\/chap6\/src\/chap6","parentWorkspace":"D:\/190812\/java","name":"ex198030.java","lastModified":1570497693564},{"path":"\/chap18\/src\/chap18","parentWorkspace":"D:\/190812\/java","name":"LambadaEx10.java","lastModified":1569986277460,"locationURI":"file:\/D:\/190812\/java\/chap18\/src\/chap18\/LambadaEx10.java"},{"path":"\/chap8\/src\/chap8","parentWorkspace":"D:\/190812\/java","name":"BikeEx2.java","lastModified":1567734174925,"locationURI":"file:\/D:\/190812\/java\/chap8\/src\/chap8\/BikeEx2.java"},{"path":"\/chap7\/src\/chap7","parentWorkspace":"D:\/190812\/java","name":"FactorialEx.java","lastModified":1567486953228,"locationURI":"file:\/D:\/190812\/java\/chap7\/src\/chap7\/FactorialEx.java"},{"path":"\/chap6\/src\/chap6","parentWorkspace":"D:\/190812\/java","name":"Exam9.java","lastModified":1570176318443},{"path":"\/chap8\/src\/chap8","parentWorkspace":"D:\/190812\/java","name":"BikeEx1.java","lastModified":1567735850155,"locationURI":"file:\/D:\/190812\/java\/chap8\/src\/chap8\/BikeEx1.java"},{"path":"\/chap6\/src\/chap6","parentWorkspace":"D:\/190812\/java","name":"Exam8.java","lastModified":1567061014859},{"path":"\/chap7\/src\/chap7","parentWorkspace":"D:\/190812\/java","name":"ex190904.java","lastModified":1567644150465,"locationURI":"file:\/D:\/190812\/java\/chap7\/src\/chap7\/ex190904.java"},{"path":"\/chap15","parentWorkspace":"D:\/190812\/java","name":"error.log","lastModified":1569392471256,"locationURI":"file:\/D:\/190812\/java\/chap15\/error.log"},{"path":"\/chap9\/src\/chap9","parentWorkspace":"D:\/190812\/java","name":"DefaultInterfaceEx1.java","lastModified":1568084466115,"locationURI":"file:\/D:\/190812\/java\/chap9\/src\/chap9\/DefaultInterfaceEx1.java"},{"path":"\/chap19\/src\/chap19","parentWorkspace":"D:\/190812\/java","name":"SortedEx1.java","lastModified":1570150794850,"locationURI":"file:\/D:\/190812\/java\/chap19\/src\/chap19\/SortedEx1.java"},{"path":"\/chap18\/src\/chap18","parentWorkspace":"D:\/190812\/java","name":"LambdaEx7.java","lastModified":1569978399383,"locationURI":"file:\/D:\/190812\/java\/chap18\/src\/chap18\/LambdaEx7.java"},{"path":"\/jdbc\/src\/jdbc","parentWorkspace":"D:\/190812\/java","name":"Exam3.java","lastModified":1568593871152,"locationURI":"file:\/D:\/190812\/java\/jdbc\/src\/jdbc\/Exam3.java"},{"path":"\/chap7\/src\/chap7","parentWorkspace":"D:\/190812\/java","name":"MathEx1.java","lastModified":1567561868409,"locationURI":"file:\/D:\/190812\/java\/chap7\/src\/chap7\/MathEx1.java"},{"path":"\/chap12\/src\/chap12","parentWorkspace":"D:\/190812\/java","name":"StringEx2.java","lastModified":1568969756958,"locationURI":"file:\/D:\/190812\/java\/chap12\/src\/chap12\/StringEx2.java"},{"path":"\/chap6\/src\/chap6","parentWorkspace":"D:\/190812\/java","name":"ArrayEx14.java","lastModified":1567406852040,"locationURI":"file:\/D:\/190812\/java\/chap6\/src\/chap6\/ArrayEx14.java"},{"path":"\/chap19\/src\/chap19","parentWorkspace":"D:\/190812\/java","name":"ProductFilesStreamEx2.java","lastModified":1570519474821,"locationURI":"file:\/D:\/190812\/java\/chap19\/src\/chap19\/ProductFilesStreamEx2.java"},{"path":"\/chap9\/src\/chap9","parentWorkspace":"D:\/190812\/java","name":"Exam2.java","lastModified":1568081277917,"locationURI":"file:\/D:\/190812\/java\/chap9\/src\/chap9\/Exam2.java"},{"path":"\/jdbc\/src\/jdbc","parentWorkspace":"D:\/190812\/java","name":"JdbcEx5.java","lastModified":1568178035708,"locationURI":"file:\/D:\/190812\/java\/jdbc\/src\/jdbc\/JdbcEx5.java"},{"path":"\/chap15\/src\/chap15","parentWorkspace":"D:\/190812\/java","name":"FileWriterEx1.java","lastModified":1569460617676,"locationURI":"file:\/D:\/190812\/java\/chap15\/src\/chap15\/FileWriterEx1.java"},{"path":"\/chap14","parentWorkspace":"D:\/190812\/java","name":"a.properties","lastModified":1569374358271,"locationURI":"file:\/D:\/190812\/java\/chap14\/a.properties"},{"path":"\/chap7\/src\/chap7","parentWorkspace":"D:\/190812\/java","name":"MemberCallEx1.java","lastModified":1567565322812,"locationURI":"file:\/D:\/190812\/java\/chap7\/src\/chap7\/MemberCallEx1.java"},{"path":"\/chap19\/src\/chap19","parentWorkspace":"D:\/190812\/java","name":"Exam1.java","lastModified":1570522878830,"locationURI":"file:\/D:\/190812\/java\/chap19\/src\/chap19\/Exam1.java"},{"path":"\/test0916\/src\/test0916","parentWorkspace":"D:\/190812\/java","name":"Family.java","lastModified":1568617626438,"locationURI":"file:\/D:\/190812\/java\/test0916\/src\/test0916\/Family.java"},{"path":"\/chap15\/src\/chap15","parentWorkspace":"D:\/190812\/java","name":"Exam4.java","lastModified":1569480673333,"locationURI":"file:\/D:\/190812\/java\/chap15\/src\/chap15\/Exam4.java"},{"path":"\/chap15\/src\/chap15","parentWorkspace":"D:\/190812\/java","name":"ObjectOutputStreamEx1.java","lastModified":1569474624801,"locationURI":"file:\/D:\/190812\/java\/chap15\/src\/chap15\/ObjectOutputStreamEx1.java"},{"path":"\/chap18\/src\/chap18","parentWorkspace":"D:\/190812\/java","name":"Exam2.java","lastModified":1569911962619,"locationURI":"file:\/D:\/190812\/java\/chap18\/src\/chap18\/Exam2.java"},{"path":"\/chap15\/src\/chap15","parentWorkspace":"D:\/190812\/java","name":"FileOutputStreamEx1.java","lastModified":1569458674873,"locationURI":"file:\/D:\/190812\/java\/chap15\/src\/chap15\/FileOutputStreamEx1.java"},{"path":"\/chap7\/src\/chap7","parentWorkspace":"D:\/190812\/java","name":"PhoneEx2.java","lastModified":1567479019561,"locationURI":"file:\/D:\/190812\/java\/chap7\/src\/chap7\/PhoneEx2.java"},{"path":"\/chap11\/src\/chap11","parentWorkspace":"D:\/190812\/java","name":"Exam3.java","lastModified":1568772081737,"locationURI":"file:\/D:\/190812\/java\/chap11\/src\/chap11\/Exam3.java"},{"path":"\/chap17\/src\/chap17","parentWorkspace":"D:\/190812\/java","name":"EchoServerEx1.java","lastModified":1569897155461,"locationURI":"file:\/D:\/190812\/java\/chap17\/src\/chap17\/EchoServerEx1.java"},{"path":"\/chap11\/src\/chap11","parentWorkspace":"D:\/190812\/java","name":"ExeptionEx2.java","lastModified":1568702756127,"locationURI":"file:\/D:\/190812\/java\/chap11\/src\/chap11\/ExeptionEx2.java"},{"path":"\/chap6\/src\/chap6","parentWorkspace":"D:\/190812\/java","name":"Exam15.java","lastModified":1570176318053,"locationURI":"file:\/D:\/190812\/java\/chap6\/src\/chap6\/Exam15.java"},{"path":"\/chap15","parentWorkspace":"D:\/190812\/java","name":"print.txt","lastModified":1569462303489,"locationURI":"file:\/D:\/190812\/java\/chap15\/print.txt"},{"path":"\/chap7\/src\/chap7","parentWorkspace":"D:\/190812\/java","name":"InitEx.java","lastModified":1567651328745,"locationURI":"file:\/D:\/190812\/java\/chap7\/src\/chap7\/InitEx.java"},{"path":"\/chap12\/src\/chap12","parentWorkspace":"D:\/190812\/java","name":"RegularEx1.java","lastModified":1569199878973,"locationURI":"file:\/D:\/190812\/java\/chap12\/src\/chap12\/RegularEx1.java"},{"path":"\/chap14\/src\/chap14","parentWorkspace":"D:\/190812\/java","name":"Exam1.java","lastModified":1570497693564,"locationURI":"file:\/D:\/190812\/java\/chap14\/src\/chap14\/Exam1.java"},{"path":"\/chap12\/src\/chap12","parentWorkspace":"D:\/190812\/java","name":"Exam3.java","lastModified":1568860649644,"locationURI":"file:\/D:\/190812\/java\/chap12\/src\/chap12\/Exam3.java"},{"path":"\/chap18\/src\/chap18","parentWorkspace":"D:\/190812\/java","name":"LambadaEx8.java","lastModified":1569979250905,"locationURI":"file:\/D:\/190812\/java\/chap18\/src\/chap18\/LambadaEx8.java"},{"path":"\/chap14\/src\/chap14","parentWorkspace":"D:\/190812\/java","name":"MapEx1.java","lastModified":1569302887910,"locationURI":"file:\/D:\/190812\/java\/chap14\/src\/chap14\/MapEx1.java"},{"path":"\/jdbc\/src\/jdbc","parentWorkspace":"D:\/190812\/java","name":"Emp.java","lastModified":1568185434913,"locationURI":"file:\/D:\/190812\/java\/jdbc\/src\/jdbc\/Emp.java"},{"path":"\/chep3\/src\/chep3","parentWorkspace":"D:\/190812\/java","name":"VarEx2.java","lastModified":1567504777574,"locationURI":"file:\/D:\/190812\/java\/chep3\/src\/chep3\/VarEx2.java"},{"path":"\/jdbc\/src\/jdbc","parentWorkspace":"D:\/190812\/java","name":"Subject.java","lastModified":1568602904632,"locationURI":"file:\/D:\/190812\/java\/jdbc\/src\/jdbc\/Subject.java"},{"path":"\/chap10\/src\/chap10","parentWorkspace":"D:\/190812\/java","name":"InnerEx2.java","lastModified":1568685190490,"locationURI":"file:\/D:\/190812\/java\/chap10\/src\/chap10\/InnerEx2.java"},{"path":"\/chap12\/src\/chap12","parentWorkspace":"D:\/190812\/java","name":"EqualsEx1.java","lastModified":1568783995685,"locationURI":"file:\/D:\/190812\/java\/chap12\/src\/chap12\/EqualsEx1.java"},{"path":"\/chap15\/src\/chap15","parentWorkspace":"D:\/190812\/java","name":"Exam1.java","lastModified":1570497693564,"locationURI":"file:\/D:\/190812\/java\/chap15\/src\/chap15\/Exam1.java"},{"path":"\/chap12\/src\/chap12","parentWorkspace":"D:\/190812\/java","name":"Test0919_1.java","lastModified":1568939992777,"locationURI":"file:\/D:\/190812\/java\/chap12\/src\/chap12\/Test0919_1.java"},{"path":"\/chap11\/src\/chap11","parentWorkspace":"D:\/190812\/java","name":"ExeptionEx7.java","lastModified":1568798044320,"locationURI":"file:\/D:\/190812\/java\/chap11\/src\/chap11\/ExeptionEx7.java"},{"path":"\/chap19\/src\/chap19","parentWorkspace":"D:\/190812\/java","name":"ProductGenerator.java","lastModified":1570157089261,"locationURI":"file:\/D:\/190812\/java\/chap19\/src\/chap19\/ProductGenerator.java"},{"path":"\/chap14\/src\/chap14","parentWorkspace":"D:\/190812\/java","name":"StackQueueEx1.java","lastModified":1569376637816,"locationURI":"file:\/D:\/190812\/java\/chap14\/src\/chap14\/StackQueueEx1.java"},{"path":"\/chap16\/src\/chap16","parentWorkspace":"D:\/190812\/java","name":"Exam4.java","lastModified":1569920776526,"locationURI":"file:\/D:\/190812\/java\/chap16\/src\/chap16\/Exam4.java"},{"path":"\/chap9\/src\/chap9","parentWorkspace":"D:\/190812\/java","name":"Exam3.java","lastModified":1568101216316,"locationURI":"file:\/D:\/190812\/java\/chap9\/src\/chap9\/Exam3.java"},{"path":"\/chap12\/src\/chap12","parentWorkspace":"D:\/190812\/java","name":"WrapperEx3.java","lastModified":1568874897375,"locationURI":"file:\/D:\/190812\/java\/chap12\/src\/chap12\/WrapperEx3.java"},{"path":"\/chap15","parentWorkspace":"D:\/190812\/java","name":"out.txt","lastModified":1569391271166,"locationURI":"file:\/D:\/190812\/java\/chap15\/out.txt"},{"path":"\/chap14\/src\/chap14","parentWorkspace":"D:\/190812\/java","name":"PropertiesEx1.java","lastModified":1569376380136,"locationURI":"file:\/D:\/190812\/java\/chap14\/src\/chap14\/PropertiesEx1.java"},{"path":"\/chap16\/src\/chap16","parentWorkspace":"D:\/190812\/java","name":"ThreadEx2.java","lastModified":1569553061886,"locationURI":"file:\/D:\/190812\/java\/chap16\/src\/chap16\/ThreadEx2.java"},{"path":"\/jdbc\/src\/jdbc","parentWorkspace":"D:\/190812\/java","name":"JdbcEx4.java","lastModified":1568171869024,"locationURI":"file:\/D:\/190812\/java\/jdbc\/src\/jdbc\/JdbcEx4.java"},{"path":"\/chap19\/src\/chap19","parentWorkspace":"D:\/190812\/java","name":"ProductFilesStreamEx.java","lastModified":1570509838086,"locationURI":"file:\/D:\/190812\/java\/chap19\/src\/chap19\/ProductFilesStreamEx.java"},{"path":"\/chap17\/src\/chap17","parentWorkspace":"D:\/190812\/java","name":"Exam1.java","lastModified":1569906021571,"locationURI":"file:\/D:\/190812\/java\/chap17\/src\/chap17\/Exam1.java"},{"path":"\/chap6\/src\/chap6","parentWorkspace":"D:\/190812\/java","name":"Exam10.java","lastModified":1567388761082},{"path":"\/chap15","parentWorkspace":"D:\/190812\/java","name":"out2.txt","lastModified":1569391838736,"locationURI":"file:\/D:\/190812\/java\/chap15\/out2.txt"},{"path":"\/chap15\/src\/chap15","parentWorkspace":"D:\/190812\/java","name":"OutputStreamEx1.java","lastModified":1569381671448,"locationURI":"file:\/D:\/190812\/java\/chap15\/src\/chap15\/OutputStreamEx1.java"},{"path":"\/chap18\/src\/chap18","parentWorkspace":"D:\/190812\/java","name":"LambadaEx5.java","lastModified":1569912647446,"locationURI":"file:\/D:\/190812\/java\/chap18\/src\/chap18\/LambadaEx5.java"},{"path":"\/chap15\/src\/chap15","parentWorkspace":"D:\/190812\/java","name":"FileEx2.java","lastModified":1569478481549,"locationURI":"file:\/D:\/190812\/java\/chap15\/src\/chap15\/FileEx2.java"},{"path":"\/chap16\/src\/chap16","parentWorkspace":"D:\/190812\/java","name":"ThreadEx7.java","lastModified":1569566365800,"locationURI":"file:\/D:\/190812\/java\/chap16\/src\/chap16\/ThreadEx7.java"},{"path":"\/chep4\/src\/chep4","parentWorkspace":"D:\/190812\/java","name":"OpEx10.java","lastModified":1570509221860,"locationURI":"file:\/D:\/190812\/java\/chep4\/src\/chep4\/OpEx10.java"},{"path":"\/chap14\/src\/chap14","parentWorkspace":"D:\/190812\/java","name":"Exam6.java","lastModified":1569311281307,"locationURI":"file:\/D:\/190812\/java\/chap14\/src\/chap14\/Exam6.java"},{"path":"\/chap7\/src\/chap7","parentWorkspace":"D:\/190812\/java","name":"Exam5.java","lastModified":1567573527540,"locationURI":"file:\/D:\/190812\/java\/chap7\/src\/chap7\/Exam5.java"},{"path":"\/chap12\/src\/chap12","parentWorkspace":"D:\/190812\/java","name":"CalendarEx3.java","lastModified":1568963849791,"locationURI":"file:\/D:\/190812\/java\/chap12\/src\/chap12\/CalendarEx3.java"},{"path":"\/chap9\/src\/chap9","parentWorkspace":"D:\/190812\/java","name":"PrinterEx1.java","lastModified":1568077891313,"locationURI":"file:\/D:\/190812\/java\/chap9\/src\/chap9\/PrinterEx1.java"},{"path":"\/chap14\/src\/chap14","parentWorkspace":"D:\/190812\/java","name":"Exam3.java","lastModified":1569221122890,"locationURI":"file:\/D:\/190812\/java\/chap14\/src\/chap14\/Exam3.java"},{"path":"\/chap14\/src\/chap14","parentWorkspace":"D:\/190812\/java","name":"SetEx3.java","lastModified":1570776999099,"locationURI":"file:\/D:\/190812\/java\/chap14\/src\/chap14\/SetEx3.java"},{"path":"\/chap15\/src\/chap15","parentWorkspace":"D:\/190812\/java","name":"ObjectInputStreamEx2.java","lastModified":1569482777469,"locationURI":"file:\/D:\/190812\/java\/chap15\/src\/chap15\/ObjectInputStreamEx2.java"},{"path":"\/chap6\/src\/chap6","parentWorkspace":"D:\/190812\/java","name":"Exam13.java","lastModified":1570497693564,"locationURI":"file:\/D:\/190812\/java\/chap6\/src\/chap6\/Exam13.java"},{"path":"\/chap12\/src\/chap12","parentWorkspace":"D:\/190812\/java","name":"StringBufferEx2.java","lastModified":1568862123719,"locationURI":"file:\/D:\/190812\/java\/chap12\/src\/chap12\/StringBufferEx2.java"},{"path":"\/chap19\/src\/chap19","parentWorkspace":"D:\/190812\/java","name":"FileToStreamEx1.java","lastModified":1570150319263,"locationURI":"file:\/D:\/190812\/java\/chap19\/src\/chap19\/FileToStreamEx1.java"},{"path":"\/chap14\/src\/chap14","parentWorkspace":"D:\/190812\/java","name":"IteratorEx1.java","lastModified":1569291371753,"locationURI":"file:\/D:\/190812\/java\/chap14\/src\/chap14\/IteratorEx1.java"},{"path":"\/chap15\/src\/chap15","parentWorkspace":"D:\/190812\/java","name":"InputStreamEx1.java","lastModified":1570497693564,"locationURI":"file:\/D:\/190812\/java\/chap15\/src\/chap15\/InputStreamEx1.java"},{"path":"\/chap7\/src\/chap7","parentWorkspace":"D:\/190812\/java","name":"OverloadEx2.java","lastModified":1567567165407,"locationURI":"file:\/D:\/190812\/java\/chap7\/src\/chap7\/OverloadEx2.java"},{"path":"\/chep4\/src\/chep4","parentWorkspace":"D:\/190812\/java","name":"OpEx1.java","lastModified":1567586230651,"locationURI":"file:\/D:\/190812\/java\/chep4\/src\/chep4\/OpEx1.java"},{"path":"\/chap12\/src\/chap12","parentWorkspace":"D:\/190812\/java","name":"StringEx4.java","lastModified":1568970025574,"locationURI":"file:\/D:\/190812\/java\/chap12\/src\/chap12\/StringEx4.java"},{"path":"\/chap11\/src\/chap11","parentWorkspace":"D:\/190812\/java","name":"Exam5.java","lastModified":1568776083634,"locationURI":"file:\/D:\/190812\/java\/chap11\/src\/chap11\/Exam5.java"},{"path":"\/chap6\/src\/chap6","parentWorkspace":"D:\/190812\/java","name":"Exam2.java","lastModified":1566973673636},{"path":"\/chap6\/src\/chap6","parentWorkspace":"D:\/190812\/java","name":"ArrayEx9.java","lastModified":1567403500674,"locationURI":"file:\/D:\/190812\/java\/chap6\/src\/chap6\/ArrayEx9.java"},{"path":"\/jdbc\/src\/jdbc","parentWorkspace":"D:\/190812\/java","name":"JdbcEx7.java","lastModified":1568612182474,"locationURI":"file:\/D:\/190812\/java\/jdbc\/src\/jdbc\/JdbcEx7.java"},{"path":"\/chap16\/src\/chap16","parentWorkspace":"D:\/190812\/java","name":"Exam1.java","lastModified":1569562594654,"locationURI":"file:\/D:\/190812\/java\/chap16\/src\/chap16\/Exam1.java"},{"path":"\/chap5\/src\/chap5","parentWorkspace":"D:\/190812\/java","name":"Exam10.java","lastModified":1566892158448},{"path":"\/chap6\/src\/chap6","parentWorkspace":"D:\/190812\/java","name":"ArrayEx12.java","lastModified":1567406852115,"locationURI":"file:\/D:\/190812\/java\/chap6\/src\/chap6\/ArrayEx12.java"},{"path":"\/chap14\/src\/chap14","parentWorkspace":"D:\/190812\/java","name":"e190924.java","lastModified":1569373331442,"locationURI":"file:\/D:\/190812\/java\/chap14\/src\/chap14\/e190924.java"},{"path":"\/chap16\/src\/chap16","parentWorkspace":"D:\/190812\/java","name":"ThreadEx12.java","lastModified":1569813089874,"locationURI":"file:\/D:\/190812\/java\/chap16\/src\/chap16\/ThreadEx12.java"},{"path":"\/chap8\/src\/chap8","parentWorkspace":"D:\/190812\/java","name":"AbstractEx1.java","lastModified":1568101200427,"locationURI":"file:\/D:\/190812\/java\/chap8\/src\/chap8\/AbstractEx1.java"},{"path":"\/chap17\/src\/chap17","parentWorkspace":"D:\/190812\/java","name":"e190930.java","lastModified":1569890955928,"locationURI":"file:\/D:\/190812\/java\/chap17\/src\/chap17\/e190930.java"}]}